hashbase/__init__.py
hashbase/crc16.py
hashbase/crc8.py
hashbase/md2.py
hashbase/md4.py
hashbase/md5.py
hashbase/ripemd128.py
hashbase/ripemd160.py
hashbase/ripemd256.py
hashbase/ripemd320.py
hashbase/sha1.py
hashbase/sha224.py
hashbase/sha256.py
hashbase/sha384.py
hashbase/sha512.py
hashbase/sha512_224.py
hashbase/sha512_256.py
hashbase/utils.py
tests/__init__.py
tests/test_crc16.py
tests/test_crc8.py
tests/test_hash_functions.py
hashbase-1.1.5.dist-info/LICENSE
hashbase-1.1.5.dist-info/METADATA
hashbase-1.1.5.dist-info/WHEEL
hashbase-1.1.5.dist-info/top_level.txt
hashbase-1.1.5.dist-info/RECORD
